{
  "db_name": "SQLite",
  "query": "SELECT * FROM posts ORDER BY updated_at DESC",
  "describe": {
    "columns": [
      {
        "name": "id",
        "ordinal": 0,
        "type_info": "Integer"
      },
      {
        "name": "title",
        "ordinal": 1,
        "type_info": "Text"
      },
      {
        "name": "slug",
        "ordinal": 2,
        "type_info": "Text"
      },
      {
        "name": "author",
        "ordinal": 3,
        "type_info": "Text"
      },
      {
        "name": "content",
        "ordinal": 4,
        "type_info": "Text"
      },
      {
        "name": "created_at",
        "ordinal": 5,
        "type_info": "Datetime"
      },
      {
        "name": "updated_at",
        "ordinal": 6,
        "type_info": "Datetime"
      }
    ],
    "parameters": {
      "Right": 0
    },
    "nullable": [
      false,
      false,
      false,
      false,
      false,
      false,
      false
    ]
  },
  "hash": "df6e050c7cf06ac944f01151a07584d3ddc0c6b432b7c518cb2a8140e9a08613"
}
