{
  "db_name": "SQLite",
  "query": "\n            SELECT\n                u.*,\n                GROUP_CONCAT(r.role) AS \"roles: String\"\n            FROM users u\n            LEFT JOIN user_roles r ON r.user_id = u.id\n            LEFT JOIN login_tokens t ON t.email = u.email\n            WHERE t.token = ?\n            GROUP BY u.id",
  "describe": {
    "columns": [
      {
        "name": "id",
        "ordinal": 0,
        "type_info": "Integer"
      },
      {
        "name": "first_name",
        "ordinal": 1,
        "type_info": "Text"
      },
      {
        "name": "last_name",
        "ordinal": 2,
        "type_info": "Text"
      },
      {
        "name": "email",
        "ordinal": 3,
        "type_info": "Text"
      },
      {
        "name": "created_at",
        "ordinal": 4,
        "type_info": "Datetime"
      },
      {
        "name": "roles: String",
        "ordinal": 5,
        "type_info": "Null"
      }
    ],
    "parameters": {
      "Right": 1
    },
    "nullable": [
      false,
      false,
      false,
      false,
      false,
      null
    ]
  },
  "hash": "54a894bd0e73b52282aa238655d9cebc4b641236dadbdb7b4a1016e23b73a842"
}
